LICENSE
MANIFEST.in
README.rst
setup.py
dj_jkabachcha.egg-info/PKG-INFO
dj_jkabachcha.egg-info/SOURCES.txt
dj_jkabachcha.egg-info/dependency_links.txt
dj_jkabachcha.egg-info/top_level.txt
jkabachcha/__init__.py
jkabachcha/db/__init__.py
jkabachcha/db/fields.py
jkabachcha/forms/__init__.py
jkabachcha/forms/widgets.py
jkabachcha/static/jkabachcha/css/jsoneditor.min.css
jkabachcha/static/jkabachcha/css/img/jsoneditor-icons.svg
jkabachcha/static/jkabachcha/js/jquery.min.js
jkabachcha/static/jkabachcha/js/jsoneditor.min.js