Metadata-Version: 1.1
Name: dj-jkabachcha
Version: 0.7
Summary: Package to create Json WYSIWYG field for Django models
Home-page: https://github.com/paytm/dj-j-ka-bachcha-field
Author: Shrey Agarwal, Taranjeet Singh
Author-email: shrey.agarwal@paytm.com, reachtotj@gmail.com
License: MIT License
Platform: UNKNOWN
Classifier: Development Status :: 4 - Beta
Classifier: Environment :: Web Environment
Classifier: Framework :: Django :: 1.8
Classifier: Intended Audience :: Developers
Classifier: License :: OSI Approved :: MIT License
Classifier: Operating System :: OS Independent
Classifier: Programming Language :: Python
Classifier: Natural Language :: English
Classifier: Programming Language :: Python :: 2.7
Classifier: Programming Language :: Python :: 3.4
Classifier: Framework :: Django :: 1.8
Classifier: Topic :: Internet :: WWW/HTTP
